flexible_matchers/__init__.py
flexible_matchers/py.typed
flexible_matchers-0.1.2.dist-info/licenses/LICENSE
flexible_matchers-0.1.2.dist-info/METADATA
flexible_matchers-0.1.2.dist-info/WHEEL
flexible_matchers-0.1.2.dist-info/top_level.txt
flexible_matchers-0.1.2.dist-info/RECORD
